dinbrief/__init__.py
dinbrief/contrib/__init__.py
dinbrief/contrib/form.py
dinbrief/contrib/qrcode.py
dinbrief/contrib/simple.py
dinbrief/document.py
dinbrief/invoice/__init__.py
dinbrief/invoice/bank_transfer_form.py
dinbrief/invoice/invoice.py
dinbrief/invoice/item.py
dinbrief/invoice/item_table.py
dinbrief/invoice/total_table.py
dinbrief/invoice/vat_item.py
dinbrief/locale/de/LC_MESSAGES/django.mo
dinbrief/locale/de/LC_MESSAGES/django.po
dinbrief/optional_django.py
dinbrief/styles.py
dinbrief/template.py
dinbrief-0.5.1.dist-info/LICENSE-APACHE
dinbrief-0.5.1.dist-info/LICENSE-BSD
dinbrief-0.5.1.dist-info/LICENSE-MIT
dinbrief-0.5.1.dist-info/METADATA
dinbrief-0.5.1.dist-info/WHEEL
dinbrief-0.5.1.dist-info/RECORD
